CHANGES.rst
MANIFEST.in
README.rst
TODO.rst
setup.cfg
setup.py
collective/__init__.py
collective.js.multizoom.egg-info/PKG-INFO
collective.js.multizoom.egg-info/SOURCES.txt
collective.js.multizoom.egg-info/dependency_links.txt
collective.js.multizoom.egg-info/entry_points.txt
collective.js.multizoom.egg-info/namespace_packages.txt
collective.js.multizoom.egg-info/not-zip-safe
collective.js.multizoom.egg-info/requires.txt
collective.js.multizoom.egg-info/top_level.txt
collective/js/__init__.py
collective/js/multizoom/__init__.py
collective/js/multizoom/configure.zcml
collective/js/multizoom/controlpanel.pt
collective/js/multizoom/controlpanel.py
collective/js/multizoom/exportimport.py
collective/js/multizoom/jqueryui_icon.jpg
collective/js/multizoom/tests.py
collective/js/multizoom/upgrades.py
collective/js/multizoom/version.txt
collective/js/multizoom/locales/collective.js.multizoom.pot
collective/js/multizoom/locales/update.sh
collective/js/multizoom/locales/en/LC_MESSAGES/collective.js.multizoom.mo
collective/js/multizoom/locales/en/LC_MESSAGES/collective.js.multizoom.po
collective/js/multizoom/locales/fr/LC_MESSAGES/collective.js.multizoom.mo
collective/js/multizoom/locales/fr/LC_MESSAGES/collective.js.multizoom.po
collective/js/multizoom/profiles/default/collective.js.multizoom.txt
collective/js/multizoom/profiles/default/collective.js.multizoom.txt~
collective/js/multizoom/profiles/default/controlpanel.xml
collective/js/multizoom/profiles/default/cssregistry.xml
collective/js/multizoom/profiles/default/import_steps.xml
collective/js/multizoom/profiles/default/import_steps.xml~
collective/js/multizoom/profiles/default/jsregistry.xml
collective/js/multizoom/profiles/default/metadata.xml
collective/js/multizoom/profiles/default/metadata.xml~
collective/js/multizoom/profiles/default/registry.xml
collective/js/multizoom/profiles/default/registry.xml~
collective/js/multizoom/profiles/plone4/cssregistry.xml
collective/js/multizoom/profiles/plone4/jsregistry.xml
collective/js/multizoom/profiles/plone5/registry.xml
collective/js/multizoom/profiles/plone5/registry.xml~
collective/js/multizoom/resources/multizoom.css
collective/js/multizoom/resources/multizoom.js
docs/INSTALL.txt
docs/LICENSE.GPL
docs/LICENSE.txt