Metadata-Version: 1.1
Name: collective.js.multizoom
Version: 2.2
Summary: collective.js.multizoom
Home-page: http://www.dynamicdrive.com/dynamicindex4/featuredzoomer.htm
Author: Martronic SA
Author-email: martronic@martronic.ch
License: GPL
Keywords: multizoom
Platform: UNKNOWN
Classifier: Framework :: Plone
Classifier: Programming Language :: Python
Classifier: Topic :: Software Development :: Libraries :: Python Modules
